dlogg_db/__init__.py
dlogg_db/common.py
dlogg_db/download.py
dlogg_db/upload.py
dlogg_db-0.3.1.dist-info/DESCRIPTION.rst
dlogg_db-0.3.1.dist-info/METADATA
dlogg_db-0.3.1.dist-info/RECORD
dlogg_db-0.3.1.dist-info/WHEEL
dlogg_db-0.3.1.dist-info/metadata.json
dlogg_db-0.3.1.dist-info/top_level.txt
